Digital_Down/__init__.py
Digital_Down/Audio/AudioNormalize.py
Digital_Down/Audio/AudioProselyte.py
Digital_Down/Audio/AudioSampleValues.py
Digital_Down/Audio/CompositionTools.py
Digital_Down/Audio/MeasurePitch.py
Digital_Down/Audio/Methylphenethylamine.py
Digital_Down/Audio/NonLinearAudio.py
Digital_Down/Audio/OperationalSynthesis.py
Digital_Down/Audio/SineAnalyze.py
Digital_Down/Audio/SurgicalSynthesis.py
Digital_Down/Audio/Waveforms.py
Digital_Down/Audio/__init__.py
Digital_Down/Code/Auto__init__.py
Digital_Down/Code/DeleteFolder.py
Digital_Down/Code/ListAutomationTools.py
Digital_Down/Code/StripFolder.py
Digital_Down/Code/TransposeFilePitchNames.py
Digital_Down/Code/__init__.py
Digital_Down/Image/AlphaImage.py
Digital_Down/Image/ImagePixelValues.py
Digital_Down/Image/ImageProselyte.py
Digital_Down/Image/__init__.py
Digital_Down/Text/AlbumMetadata.py
Digital_Down/Text/Documentation.py
Digital_Down/Text/LicenseGenerator.py
Digital_Down/Text/SongMetadata.py
Digital_Down/Text/__init__.py
Digital_Down/Video/AlphaOverVideo.py
Digital_Down/Video/AlphaVideo.py
Digital_Down/Video/FramesToVideo.py
Digital_Down/Video/MindHarvestNetwork.py
Digital_Down/Video/PhaneronTracker.py
Digital_Down/Video/VideoPixelValues.py
Digital_Down/Video/__init__.py
Digital_Down-5.0.3.dist-info/LICENSE.txt
Digital_Down-5.0.3.dist-info/METADATA
Digital_Down-5.0.3.dist-info/WHEEL
Digital_Down-5.0.3.dist-info/top_level.txt
Digital_Down-5.0.3.dist-info/RECORD
